{
  "resourceType": "Observation",
  "id": "BFS-Hospital-Admission-Mobility-SelfCare-1-Ob-Question-26",
  "meta": {
    "profile": [
      "http://hl7.org/fhir/us/pacio-fs/StructureDefinition/pacio-fs"
    ]
  },
  "extension": [
    {
      "url": "http://hl7.org/fhir/StructureDefinition/event-location",
      "valueReference": {
        "reference": "Location/Org-Loc-01"
      }
    }
  ],
  "subject": {
    "reference": "Patient/patientBSJ1"
  },
  "status": "final",
  "effectiveDateTime": "2020-07-08T16:00:00-05:00",
  "code": {
    "coding": [
      {
        "code": "83222-0",
        "system": "http://loinc.org",
        "display": "Lower body dressing - functional ability during 3D assessment period"
      }
    ],
    "text": "Lower body dressing"
  },
  "valueCodeableConcept": {
    "coding": [
      {
        "code": "LA26735-3",
        "system": "http://loinc.org",
        "display": "Not Attempted"
      }
    ],
    "text": "Not Attempted"
  },
  "performer": [
    {
      "reference": "Practitioner/Practitioner-SallySmith"
    },
    {
      "reference": "PractitionerRole/Role-PT"
    },
    {
      "reference": "Organization/Org-01",
      "display": "Organization"
    }
  ],
  "derivedFrom": [
    {
      "reference": "QuestionnaireResponse/QResponse-Hospital-Admission-Mobility-SelfCare-1"
    }
  ]
}
